MANIFEST.in
README.rst
setup.py
cloudconf/__init__.py
cloudconf/userdata.py
cloudconf.egg-info/PKG-INFO
cloudconf.egg-info/SOURCES.txt
cloudconf.egg-info/dependency_links.txt
cloudconf.egg-info/top_level.txt