Metadata-Version: 1.1
Name: cloudconf
Version: 0.1
Summary: Simple helper library for ubuntu's cloudinit.
Home-page: https://github.com/phobologic/cloudconf
Author: Michael Barrett
Author-email: loki77@gmail.com
License: New BSD license
Platform: UNKNOWN
Classifier: License :: OSI Approved :: BSD License
Classifier: Development Status :: 3 - Alpha
